README.md
setup.py
kerop/__init__.py
kerop/profile.py
kerop.egg-info/PKG-INFO
kerop.egg-info/SOURCES.txt
kerop.egg-info/dependency_links.txt
kerop.egg-info/top_level.txt
kerop.egg-info/zip-safe