Metadata-Version: 2.1
Name: kerop
Version: 0.1.4-2010260808
Summary: Counts the number of OPS in your Keras model.
Home-page: https://github.com/kentaroy47/keras-Opcounter
Author: Kentaro Yoshioka
Author-email: meathouse47@gmail.com
License: MIT
Platform: UNKNOWN
Classifier: Programming Language :: Python :: 3
